dhenara/__init__.py
dhenara/ai/__init__.py
dhenara/ai/ai_client/__init__.py
dhenara/ai/ai_client/_decorators.py
dhenara/ai/ai_client/ai_client.py
dhenara/ai/ai_client/factory.py
dhenara/ai/config/__init__.py
dhenara/ai/config/default_settings.py
dhenara/ai/libs/fns.py
dhenara/ai/providers/__init__.py
dhenara/ai/providers/anthropic/__init__.py
dhenara/ai/providers/anthropic/base.py
dhenara/ai/providers/anthropic/chat.py
dhenara/ai/providers/anthropic/formatter.py
dhenara/ai/providers/anthropic/message_converter.py
dhenara/ai/providers/base/__init__.py
dhenara/ai/providers/base/base.py
dhenara/ai/providers/base/base_formatter.py
dhenara/ai/providers/base/base_message_converter.py
dhenara/ai/providers/base/streaming_manager.py
dhenara/ai/providers/common/__init__.py
dhenara/ai/providers/common/dummy.py
dhenara/ai/providers/google/__init__.py
dhenara/ai/providers/google/base.py
dhenara/ai/providers/google/chat.py
dhenara/ai/providers/google/formatter.py
dhenara/ai/providers/google/image.py
dhenara/ai/providers/google/message_converter.py
dhenara/ai/providers/openai/__init__.py
dhenara/ai/providers/openai/base.py
dhenara/ai/providers/openai/constants.py
dhenara/ai/providers/openai/formatter.py
dhenara/ai/providers/openai/image.py
dhenara/ai/providers/openai/message_converter.py
dhenara/ai/providers/openai/responses.py
dhenara/ai/providers/openai/legacy_chat_api/chat.py
dhenara/ai/providers/openai/legacy_chat_api/formatter.py
dhenara/ai/providers/openai/legacy_chat_api/message_converter.py
dhenara/ai/providers/shared/__init__.py
dhenara/ai/providers/shared/shared.py
dhenara/ai/testing/__init__.py
dhenara/ai/testing/artifact_manager.py
dhenara/ai/types/__init__.py
dhenara/ai/types/conversation/__init__.py
dhenara/ai/types/conversation/_node.py
dhenara/ai/types/genai/__init__.py
dhenara/ai/types/genai/ai_model/__init__.py
dhenara/ai/types/genai/ai_model/_ai_model.py
dhenara/ai/types/genai/ai_model/_ai_model_api.py
dhenara/ai/types/genai/ai_model/_ai_model_ep.py
dhenara_ai-1.1.2.dist-info/METADATA
dhenara_ai-1.1.2.dist-info/WHEEL
dhenara_ai-1.1.2.dist-info/RECORD
