Metadata-Version: 2.4
Name: dhenara-ai
Version: 1.1.2
Summary: Dhenara Package for Multi Provider AI-Model API calls
Project-URL: Homepage, https://dhenara.com
Project-URL: Documentation, https://docs.dhenara.com/
Project-URL: Bug Reports, https://github.com/dhenara/dhenara-ai/issues
Project-URL: Source Code, https://github.com/dhenara/dhenara-ai
Author-email: Dhenara Inc <support@dhenara.com>
License-Expression: MIT
Keywords: ai,language models,llm,machine learning
Classifier: Development Status :: 4 - Beta
Classifier: Intended Audience :: Developers
Classifier: License :: OSI Approved :: MIT License
Classifier: Operating System :: OS Independent
Classifier: Programming Language :: Python :: 3
Classifier: Programming Language :: Python :: 3.13
Classifier: Topic :: Scientific/Engineering :: Artificial Intelligence
Requires-Python: <3.14,>=3.13
Requires-Dist: aiohttp>=3.11.0
Requires-Dist: anthropic>=0.69.0
Requires-Dist: asgiref>=3.8.0
Requires-Dist: azure-ai-inference>=1.0.0b9
Requires-Dist: boto3>=1.40.51
Requires-Dist: botocore>=1.40.51
Requires-Dist: cryptography>=44.0.0
Requires-Dist: google-genai>=1.43.0
Requires-Dist: httpx>=0.28.0
Requires-Dist: openai>=2.3.0
Requires-Dist: pillow>=11.1.0
Requires-Dist: pydantic>=2.10.0
Requires-Dist: pyyaml>=6.0
Requires-Dist: requests>=2.32.1
Provides-Extra: dev
Requires-Dist: add-trailing-comma; extra == 'dev'
Requires-Dist: black; extra == 'dev'
Requires-Dist: pytest-asyncio; extra == 'dev'
Requires-Dist: pytest-cov; extra == 'dev'
Requires-Dist: pytest>=7.0.0; extra == 'dev'
Requires-Dist: ruff; extra == 'dev'
